progrow/__init__.py
progrow/layout.py
progrow/py.typed
progrow/row.py
progrow/rows.py
progrow/style.py
progrow/version.py
progrow-1.0.1.dist-info/LICENSE
progrow-1.0.1.dist-info/METADATA
progrow-1.0.1.dist-info/WHEEL
progrow-1.0.1.dist-info/top_level.txt
progrow-1.0.1.dist-info/RECORD
