Metadata-Version: 2.1
Name: progrow
Version: 1.0.1
Summary: Graphs the progress of work across rows
Home-page: https://github.com/cariad/progrow
Author: Cariad Eccleston
Author-email: cariad@hey.com
License: MIT License
Platform: UNKNOWN
Classifier: Development Status :: 5 - Production/Stable
Classifier: Intended Audience :: Developers
Classifier: License :: OSI Approved :: MIT License
Classifier: Natural Language :: English
Classifier: Operating System :: OS Independent
Classifier: Programming Language :: Python :: 3 :: Only
Classifier: Programming Language :: Python :: 3.6
Classifier: Programming Language :: Python :: 3.7
Classifier: Programming Language :: Python :: 3.8
Classifier: Programming Language :: Python :: 3.9
Classifier: Typing :: Typed
Requires-Python: >=3.6
Requires-Dist: colorama (~=0.4.4)
